<?xml version="1.0" encoding="UTF-8"?>
<locale version="2" product="eWebEditPro" xml:lang="nl" xsi:noNamespaceSchemaLocation="locale.xsd" xmlns:xsi="http://www.w3.org/2001/XMLSchema-instance">
<custom>
<!--define custom 'ts' elements here with a unique id-->
</custom>
<standard>
<ts id="abt">Info</ts>
<ts id="abtEd">On-line WYSIWYG editor</ts>
<ts id="abtIL">ONGELDIGE LICENTIE</ts>
<ts id="abtImg"></ts>
<ts id="abtLN">&amp;Licentienummers:</ts>
<ts id="bkm">Boekmerk</ts>
<ts id="bkmAdd">&amp;Toevoegen</ts>
<ts id="bkmDel">&amp;Verwijderen</ts>
<ts id="bkmEnt">Voer nieuwe naam in:</ts>
<ts id="bkmGo">&amp;Ga naar</ts>
<ts id="bkmNam">&amp;Boekmerk naam:</ts>
<ts id="bkmRB">Andere naam boekmerk</ts>
<ts id="bkmRen">&amp;Andere naam</ts>
<ts id="btnCapAC">Midden</ts>
<ts id="btnCapAL">Links</ts>
<ts id="btnCapAR">Rechts</ts>
<ts id="btnCapBul">Bullets</ts>
<ts id="btnCapClean">Schoon</ts>
<ts id="btnCapGlyph">Glyphs</ts>
<ts id="btnCapHdg">Heading</ts>
<ts id="btnCapHR">HR</ts>
<ts id="btnCapIndl">Uitsprong</ts>
<ts id="btnCapIndr">Insprong</ts>
<ts id="btnCapnbsp">nbsp</ts>
<ts id="btnCapNumL">Nummers</ts>
<ts id="btnCapShBord">Randen</ts>
<ts id="btnCapTM">TM</ts>
<ts id="cln">Schoon</ts>
<ts id="clnDone">Het leegmaken van de bron is voltooid.</ts>
<ts id="clnErr2">eWebEditPro kan het document niet reinigen totdat deze fouten zijn hersteld:</ts>
<ts id="clnFiltTag">Reinigen van tags...</ts>
<ts id="clnSource">Bron leegmaken</ts>
<ts id="clnWord2000">Verwijderen van extra Word 2000 inhoud...</ts>
<ts id="cmdAbt">Info over eWebEditPro</ts>
<ts id="cmdAC">Lijn op in midden</ts>
<ts id="cmdAL">Lijn op naar links</ts>
<ts id="cmdAR">Lijn op naar rechts</ts>
<ts id="cmdBkm">Bookmark</ts>
<ts id="cmdBold">Vet</ts>
<ts id="cmdBul">Lijst met bullets</ts>
<ts id="cmdC169">Copyright</ts>
<ts id="cmdC174">Geregistreerd handelsmerk</ts>
<ts id="cmdClean">Gereinigde inhoud</ts>
<ts id="cmdCp">Kopiëren</ts>
<ts id="cmdCut">Knippen</ts>
<ts id="cmdDel">Verwijderen</ts>
<ts id="cmdExtCh">Speciale tekens</ts>
<ts id="cmdFC">Lettertype kleur</ts>
<ts id="cmdFCVal">Tekstkleur Lijst</ts>
<ts id="cmdFind">Zoeken</ts>
<ts id="cmdFNm">Lettertype naam</ts>
<ts id="cmdFS">Lettertype grootte</ts>
<ts id="cmdGlyph">Toon onzichtbare elementen</ts>
<ts id="cmdHdg">Paragraaf formaat</ts>
<ts id="cmdHR">Horizontale lijn</ts>
<ts id="cmdHyp">Hyperlink</ts>
<ts id="cmdIndl">Maak insprong kleiner</ts>
<ts id="cmdIndr">Maak insprong groter</ts>
<ts id="cmdItal">Cursief</ts>
<ts id="cmdMore">Meer</ts>
<ts id="cmdnbsp">Niet-brekende spatie</ts>
<ts id="cmdNewHyp">Nieuwe hyperlink</ts>
<ts id="cmdNumL">Genummerde lijst</ts>
<ts id="cmdPas">Plakken-</ts>
<ts id="cmdPic">Afbeelding</ts>
<ts id="cmdRedo">Opnieuw</ts>
<ts id="cmdReplace">Vervangen</ts>
<ts id="cmdShBord">Toon randen</ts>
<ts id="cmdSplayt">Controleer spelling tijdens typen</ts>
<ts id="cmdSplck">Controleer spelling</ts>
<ts id="cmdStrike">Doorhalen</ts>
<ts id="cmdStyle">Stijl</ts>
<ts id="cmdSub">Subscript</ts>
<ts id="cmdSup">Superscript</ts>
<ts id="cmdTbl">Tabel</ts>
<ts id="cmdTM">Handelsmerk</ts>
<ts id="cmdUndln">Onderstrepen</ts>
<ts id="cmdUndo">Ongedaan maken</ts>
<ts id="cmdUnlnk">Verwijder link</ts>
<ts id="cmdVAH">Bekijken bron</ts>
<ts id="cmdVAProp">Bekijk voorkeuren</ts>
<ts id="cmdVAW">Weergeven als WYSIWYG</ts>
<ts id="colorAqua">Aqua</ts>
<ts id="colorBlack">Zwart</ts>
<ts id="colorBlue">Blauw</ts>
<ts id="colorFuchsia">Fuchsia</ts>
<ts id="colorGray">Grijs</ts>
<ts id="colorGreen">Groen</ts>
<ts id="colorLime">Limoen</ts>
<ts id="colorMaroon">Kastanjebruin</ts>
<ts id="colorNavy">Navy</ts>
<ts id="colorOlive">Olijfgroen</ts>
<ts id="colorPal">Kleurenpalet</ts>
<ts id="colorPurple">Paars</ts>
<ts id="colorRed">Rood</ts>
<ts id="colorSilver">Zilver</ts>
<ts id="colorTeal">Blauw-groen</ts>
<ts id="colorWhite">Wit</ts>
<ts id="colorYellow">Geel</ts>
<ts id="errdlgshow">Er zat een fout in de dialoog.  De gebruiker installatie voor de editor moet misschien worden gestart om het probleem te corrigeren.</ts>
<ts id="filAsk">Wilt u de broncode nu leegmaken?</ts>
<ts id="filExam">Broncode controleren </ts>
<ts id="filMsg">Dit kan, afhankelijk van de grootte van uw document, tussen enkele seconden en een minuut of langer duren.</ts>
<ts id="filOut">Broncode voorbereiden</ts>
<ts id="filReduc">Broncode reduceren</ts>
<ts id="filRHtml">Broncode leegmaken</ts>
<ts id="filTxt1">Kopiëren en plakken kan ertoe leiden dat de broncode onnodig of incompatibel is.</ts>
<ts id="filTxt2">Er is een door Office 2000 gegenereerde broncode gesignaleerd</ts>
<ts id="filTxt3">De broncode is te uitgebreid, waardoor het wellicht onmogelijk is de tekstindeling te wijzigen.</ts>
<ts id="filTxt4">U kunt de broncode later wijzigen door met de rechtermuisknop te klikken op 'Broncode leegmaken' en deze te selecteren.</ts>
<ts id="filWait">Even geduld s.v.p....</ts>
<ts id="filWF">Lege bron aanmaken...</ts>
<ts id="filXhtml">Creëren van XHTML...</ts>
<ts id="find">Zoeken</ts>
<ts id="findAgain">Nogmaals zoeken vanaf begin van document?</ts>
<ts id="findAndRepl">Zoeken en vervangen</ts>
<ts id="findCase">Hoofd-/kleine letters (&amp;C)</ts>
<ts id="findFound">Gezochte tekst is gevonden. Vervangingen:</ts>
<ts id="findNext">Volgende &amp;Zoeken </ts>
<ts id="findNFound">Gezochte tekst is niet gevonden.</ts>
<ts id="findWhat">Zo&amp;eken naar:</ts>
<ts id="findWhole">&amp;Heel woord</ts>
<ts id="htm">Bron</ts>
<ts id="htmlbl">Bron:</ts>
<ts id="hyp">Hyperlink</ts>
<ts id="hypBkm">&amp;Bladwijzer:</ts>
<ts id="hypInfo">Hyperlink informatie</ts>
<ts id="hypLink">&amp;Link:</ts>
<ts id="hypOther">(andere)</ts>
<ts id="hypQL">&amp;Snelle link:</ts>
<ts id="hypSL">(selecteer link)</ts>
<ts id="hypTarg">Doel &amp;raam:</ts>
<ts id="hypTargB">Nieuw venster (_blank)</ts>
<ts id="hypTargP">Hoofdvebster (_hoofd)</ts>
<ts id="hypTargS">Zelfde venster (_zelf)</ts>
<ts id="hypTargT">Browser venster (_top)</ts>
<ts id="hypTop">Top</ts>
<ts id="hypTP">(deze pagina)</ts>
<ts id="hypTxt">&amp;Tekst:</ts>
<ts id="hypTyp">Typ&amp;e:</ts>
<ts id="initworking">De inhoud van de pagina is nog bezig te initialiseren. Even geduld s.v.p....</ts>
<ts id="licCont">Niet mogelijk in container te draaien: </ts>
<ts id="licExp">Licentie is verlopen per datum: </ts>
<ts id="licHost">Er is een licentie vereist voor host: </ts>
<ts id="licReq">Internet Explorer 4.0 of later is vereist.</ts>
<ts id="loaddhtmlerr">De editor was niet in staat om de DHTML Editor te creëren.

Laat s.v.p. de client installatie draaien of neem contact op met uw systeemadministrator.</ts>
<ts id="loadsourceerr">De editor kon de Editor Bron Bekijken niet aanmaken. Draai de client-installatie of neem contact op met uw systeembeheerder.</ts>
<ts id="loadtoolbarerr">De editor was niet in staat om de toolbar te creëren.

Laat s.v.p. de client installatie draaien of neem contact op met uw systeemadministrator.</ts>
<ts id="mfoDom">&amp;Domein</ts>
<ts id="mfoLI">Gebruikersnaam</ts>
<ts id="mfoName">&amp;Naam</ts>
<ts id="mfoPort">P&amp;oort</ts>
<ts id="mfoPS">Pro&amp;xy server</ts>
<ts id="mfoPwd">Pas&amp;woord</ts>
<ts id="mfoSrv">Server</ts>
<ts id="mnuBT">Bodytekst</ts>
<ts id="mnuCapt">Bijschrift</ts>
<ts id="mnuClean">Bron leegmaken</ts>
<ts id="mnuCp">Kopiëren</ts>
<ts id="mnuCProp">Celeigenschappen...</ts>
<ts id="mnuCustomize">Aanpassen...</ts>
<ts id="mnuCut">Knippen</ts>
<ts id="mnuDCell">Verwijderen cellen</ts>
<ts id="mnuDCol">Verwijderen kolommen</ts>
<ts id="mnuDel">Verwijderen</ts>
<ts id="mnuDRow">Verwijderen rijen</ts>
<ts id="mnuEdit">Bewerken</ts>
<ts id="mnuEHtm">Bron wijzigen</ts>
<ts id="mnuFil">Broncode leegmaken...</ts>
<ts id="mnuFmt">Formaat</ts>
<ts id="mnuFS1">1 (8 pt)</ts>
<ts id="mnuFS2">2 (10 pt)</ts>
<ts id="mnuFS3">3 (12 pt)</ts>
<ts id="mnuFS4">4 (14 pt)</ts>
<ts id="mnuFS5">5 (18 pt)</ts>
<ts id="mnuFS6">6 (24 pt)</ts>
<ts id="mnuFS7">7 (36 pt)</ts>
<ts id="mnuHTML">Bekijken bron</ts>
<ts id="mnuHyp">Hyperlink</ts>
<ts id="mnuICell">Invoegen cel</ts>
<ts id="mnuICol">Invoegen kolom</ts>
<ts id="mnuIHtm">Bron invoegen</ts>
<ts id="mnuImgA">Figuur eigenschappen</ts>
<ts id="mnuIRow">Invoegen rij</ts>
<ts id="mnuITbl">Invoegen tabel</ts>
<ts id="mnuMC">Samenvoegen cellen</ts>
<ts id="mnuNorm">Normaal</ts>
<ts id="mnuPas">Invoegen</ts>
<ts id="mnuPFmt">Paragraaf formaat</ts>
<ts id="mnuPic">Afbeelding</ts>
<ts id="mnuPlainT">Normale tekst</ts>
<ts id="mnuPt">pt</ts>
<ts id="mnuSC">Splitsen cel</ts>
<ts id="mnuSelA">Selecteer alle</ts>
<ts id="mnuSpl">Controleer spelling</ts>
<ts id="mnuSplChr">Speciale tekens</ts>
<ts id="mnuSttl">Ondertitel</ts>
<ts id="mnuTProp">Tabel eigenschappen...</ts>
<ts id="mnuTtl">Titel</ts>
<ts id="mnuVHtm">Bekijken bron</ts>
<ts id="mnuViewAs">Weergeven als</ts>
<ts id="mnuVPref">Voorkeuren...</ts>
<ts id="mnuWYS">Weergeven als WYSIWYG</ts>
<ts id="pcp">Selecteer fotobestand</ts>
<ts id="pcpAF">Alle bestanden</ts>
<ts id="pcpBr">B&amp;rowse...</ts>
<ts id="pcpCA">Copiëer &amp;als:</ts>
<ts id="pcpCp">&amp;Kopiëren</ts>
<ts id="pcpCpF">Bezig met kopiëren van bestand, even geduld s.v.p....</ts>
<ts id="pcpEFC">Storing tijdens kopiëren van bestand</ts>
<ts id="pcpErrCp">Kopiëren van bestand mislukt. Storing: </ts>
<ts id="pcpF">Bestand: </ts>
<ts id="pcpFE">Bestand bestaat</ts>
<ts id="pcpFN">Bestan&amp;dsnaam:</ts>
<ts id="pcpFS">FTP setup</ts>
<ts id="pcpFSb">FTP &amp;setup &gt;&gt;</ts>
<ts id="pcpGJ">GIF en JPEG</ts>
<ts id="pcpIns">Er moet een kopie van het fotobestand op de website zijn geplaatst om uw webpagina correct te kunnen weergeven.</ts>
<ts id="pcpMFN">Ontbrekende bestandsnaam.</ts>
<ts id="pcpMPN">Ontbrekende fotonaam.</ts>
<ts id="pcpNA">Bestand niet geaccepteerd.</ts>
<ts id="pcpNDat">Bestand bevat geen gegevens.</ts>
<ts id="pcpNF">Bestand kon niet worden gevonden.</ts>
<ts id="pcpNot">Bestand kon niet worden gekopieerd.</ts>
<ts id="pcpNPic">Bestand is geen fotobestand.</ts>
<ts id="pcpNResp">Geen antwoord van server.</ts>
<ts id="pcpNSFS">Geen toegang tot server bestands-systeem.</ts>
<ts id="pcpPic">&amp;Foto:</ts>
<ts id="pcpPict">Foto</ts>
<ts id="pcpPM">Passieve &amp;mode FTP</ts>
<ts id="pcpPNG">Portable Network Graphics</ts>
<ts id="pcpPS">Pro&amp;xy server:</ts>
<ts id="pcpPvw">Pre&amp;view</ts>
<ts id="pcpREF">Bestaand bestand vervangen?</ts>
<ts id="pcpTo">Aan:   </ts>
<ts id="pcpUN">&amp;Gebruikersnaam met FTP host, bijvoorbeeld, user@ftp.remotehost</ts>
<ts id="pic">Foto</ts>
<ts id="picAccOpt">Bestand toegangsopties</ts>
<ts id="picAli">&amp;Uitlijning:</ts>
<ts id="picAliAB">Absonder</ts>
<ts id="picAliAM">Absmidden</ts>
<ts id="picAliB">Onderkant</ts>
<ts id="picAliBL">Basislijn</ts>
<ts id="picAliL">Links</ts>
<ts id="picAliM">Midden</ts>
<ts id="picAliR">Rechts</ts>
<ts id="picAliT">Top</ts>
<ts id="picAliTT">Bovenkant tekst</ts>
<ts id="picApply">&amp;Aanwenden</ts>
<ts id="picBT">&amp;Dikte rand:</ts>
<ts id="picErrLoc">Fout bij lokaliseren van fotobestand.</ts>
<ts id="picFailedConnect">Sorry, de verbinding kon niet worden totstandgebracht.

Controleer s.v.p. of de login en verbindingsinformatie juist zijn.</ts>
<ts id="picFailedUpload">Fout bij het uploaden van het geselecteerde bestand.
Het uploaden van bestanden is op deze lokatie misschien niet toegestaan.

Controleer s.v.p. of de settings voor de verbinding en server permissies juist zijn.</ts>
<ts id="picFile">Bestan&amp;dskeuze</ts>
<ts id="picHt">&amp;Hoogte:</ts>
<ts id="picHz">H&amp;orizontaal:</ts>
<ts id="picInsertFile">&amp;Invoegen bestand</ts>
<ts id="picLay">Layout</ts>
<ts id="picLblImages">&amp;Figuur:</ts>
<ts id="picLoc">&amp;Lokatie:</ts>
<ts id="picNF">Kon het fotobestand niet vinden.</ts>
<ts id="picNS">Niet ingesteld</ts>
<ts id="picObtImg">Binnenhalen figuur </ts>
<ts id="picObtList">Binnenhalen van lijst van beschikbare figuur</ts>
<ts id="picOpt">&amp;Opties</ts>
<ts id="picoptcnfm">Bevestig &amp;voor het uploaden</ts>
<ts id="picoptdestroot">T&amp;ransfer lokatie</ts>
<ts id="picoptdlg">Opties</ts>
<ts id="picoptdlgsimple">Upload en van login informatie</ts>
<ts id="picoptlocal">Lokaal</ts>
<ts id="picoptmaxsz">Maximum bestandsgrootte (kB)</ts>
<ts id="picoptmethod">&amp;Methode</ts>
<ts id="picoptpassv">Passi&amp;eve mode</ts>
<ts id="picoptremote">Op afstand</ts>
<ts id="picoptresfull">V&amp;olle padresolutie</ts>
<ts id="picoptresgiven">Relatief t.o.v. g&amp;egeven lokatie:</ts>
<ts id="picoptresgrp">Bestandsreferentie padresolutie</ts>
<ts id="picoptreshost">Relatief t.o.v. &amp;host</ts>
<ts id="picoptreslocal">&amp;Lokaal t.o.v. pagina</ts>
<ts id="picoptsrcdir">&amp;Brondirectory</ts>
<ts id="picoptsubdir">Toestaan van subdirectories</ts>
<ts id="picoptupmech">Transfer</ts>
<ts id="picoptvalext">Geldige extensies</ts>
<ts id="picoptwebroot">&amp;Web referentie</ts>
<ts id="picPCL">Controleer s.v.p. de lokatie en probeer het nogmaals.</ts>
<ts id="picPic">&amp;Foto:</ts>
<ts id="picPlsWait"> : Even wachten s.v.p.... Bezig met binnenhalen bestandslijst</ts>
<ts id="picPrevw">Klik hier voor preview</ts>
<ts id="picPW">Preview</ts>
<ts id="picRes">Beginwaarde (&amp;R)</ts>
<ts id="picResPaths">Oplossen van figuur &amp;paden</ts>
<ts id="picSel">(Selecteer Figuur)</ts>
<ts id="picSelDlg">Foto eigenschappen</ts>
<ts id="picSelectFile">Kies &amp;nw. best</ts>
<ts id="picSpa">Spatie</ts>
<ts id="picTO">Timed out tijdens proberen fotobestand te lokaliseren.</ts>
<ts id="picTooLg">Het geselecteerde bestand is te groot om te kunnen worden geupload.

De maximale grootte is </ts>
<ts id="picTtl">&amp;Titel:</ts>
<ts id="picVt">&amp;Verticaal:</ts>
<ts id="picWd">&amp;Breedte:</ts>
<ts id="popStyle">Populating style informatie...</ts>
<ts id="reswtool">Hertonen van toolbars</ts>
<ts id="sizGB">gB</ts>
<ts id="sizKB">kB</ts>
<ts id="sizMB">mB</ts>
<ts id="spl">Spelling</ts>
<ts id="splChg">&amp;Wijzigen</ts>
<ts id="splChgA">Wijzigen al&amp;le</ts>
<ts id="splContFin">Klaar met het checken van de keuze. Wilt u de rest van het document controleren?</ts>
<ts id="splContRest">Wilt u de rest van het document controleren?</ts>
<ts id="splCS">Controleer spelling</ts>
<ts id="splDone">Het controleren van de spelling is voltooid.</ts>
<ts id="splIgn">&amp;Negeren</ts>
<ts id="splIgnA">&amp;Negeer alle</ts>
<ts id="splND">Niet in woordenboek&amp;:</ts>
<ts id="splNot">Onmogelijk om spelling te controleren.</ts>
<ts id="splNSug">(geen spellingsvoorstellen)</ts>
<ts id="splReq">Microsoft Word 97 of later is vereist.</ts>
<ts id="splReqAlt">Niet mogelijk om speciaal woordenboek voor deze eWebEditPro installatie te creëren.</ts>
<ts id="splSug">Sugg&amp;esties:</ts>
<ts id="splUE">&amp;Undo edit</ts>
<ts id="stdAdvanced">&amp;Gevorderd</ts>
<ts id="stdAllFilTyp">Alle typen bestanden</ts>
<ts id="stdCancel">Annuleren</ts>
<ts id="stdCharset">1</ts>
<ts id="stdClose">Sluiten</ts>
<ts id="stdErr">Storing</ts>
<ts id="stdFont">MS Sans Serif</ts>
<ts id="stdFontSize">8</ts>
<ts id="stdOK">OK</ts>
<ts id="styNoRules">Geen actieve regels</ts>
<ts id="tabmfuconn">&amp;Verbinding</ts>
<ts id="tabmfulimits">&amp;Grenzen</ts>
<ts id="tabmfupaths">&amp;Paden</ts>
<ts id="tabmfuxfer">&amp;Transfer</ts>
<ts id="tbl">Tabel</ts>
<ts id="tblBC">R&amp;andkleur:</ts>
<ts id="tblBgC">Ach&amp;tergrondkleur:</ts>
<ts id="tblBgImg">Achtergrond &amp;figuur:</ts>
<ts id="tblBord">Randen</ts>
<ts id="tblBS">Ran&amp;dgrootte:</ts>
<ts id="tblCBg">Eigen achtergrond</ts>
<ts id="tblCol">&amp;Kolommen:</ts>
<ts id="tblCPad">&amp;Cel vrije ruimte tot rand:</ts>
<ts id="tblCProp">Celeigenschappen</ts>
<ts id="tblCS">&amp;Overbrugde kolommen:</ts>
<ts id="tblCSp">Cel vrije rui&amp;mte:</ts>
<ts id="tblDC">Gebruik &amp;van standaard kleur</ts>
<ts id="tblFile">&amp;Van bestand File...</ts>
<ts id="tblHA">Horizontale &amp;uitlijning:</ts>
<ts id="tblHAC">midden</ts>
<ts id="tblHAJ">gecentreerd</ts>
<ts id="tblHAL">links</ts>
<ts id="tblHAR">rechts</ts>
<ts id="tblInsTbl">Invoegen tabel</ts>
<ts id="tblLay">Layout</ts>
<ts id="tblNS">&amp;Niet gespecificeerd</ts>
<ts id="tblPct">Pe&amp;rcentage</ts>
<ts id="tblPx">Pi&amp;xels</ts>
<ts id="tblRow">Rij&amp;en:</ts>
<ts id="tblRS">&amp;Overbrugde rijen:</ts>
<ts id="tblSpan">Overbruggen</ts>
<ts id="tblSz">Grootte</ts>
<ts id="tblTProp">Tabel eigenschappen</ts>
<ts id="tblUA">N&amp;iet toegekend</ts>
<ts id="tblVA">&amp;Verticale uitlijning:</ts>
<ts id="tblVAB">onderkant</ts>
<ts id="tblVABL">basislijn</ts>
<ts id="tblVAM">midden</ts>
<ts id="tblVAT">top</ts>
<ts id="tblWd">&amp;Breedte:</ts>
<ts id="tblWrap">Woor&amp;d omslaan</ts>
<ts id="tbr">Toolbar aanpassing aan persoonlijke smaak</ts>
<ts id="tbrAdd">&lt;-- &amp;Toevoegen</ts>
<ts id="tbrAllCmds">Alle co&amp;mmandos</ts>
<ts id="tbrBar">Balk</ts>
<ts id="tbrBars">Tool&amp;bars</ts>
<ts id="tbrCmds">Tool&amp;bar commandos</ts>
<ts id="tbrCnfDel">Bent u er zeker van dat u deze toolbar wilt verwijderen?</ts>
<ts id="tbrCnfRst">Het resetten van de toolbars heeft tot gevolg dat alle settings op hun vooringestelde waarden teruggezet worden.
Alle persoonlijke ingestelde waarden kunnen verloren gaan.

Wilt u doorgaan?</ts>
<ts id="tbrDel">&amp;Verwijderen</ts>
<ts id="tbrDn">Beweeg &amp;omlaag</ts>
<ts id="tbrNew">&amp;Nieuw</ts>
<ts id="tbrRem">&amp;Verwijderen --&gt;</ts>
<ts id="tbrResAll">Beginwaarde alle</ts>
<ts id="tbrReset">Beginwaarde alle (&amp;R)</ts>
<ts id="tbrSel">Geen toolbar geselecteerd.</ts>
<ts id="tbrSelTbr">Geselecteerde toolbar</ts>
<ts id="tbrSp">Spatie</ts>
<ts id="tbrTabCmd">&amp;Commandos</ts>
<ts id="tbrTabTbr">&amp;Toolbars</ts>
<ts id="tbrTbr">Tool&amp;bar:</ts>
<ts id="tbrUp">Beweeg &amp;omhoog</ts>
<ts id="txtHdg1">Heading 1</ts>
<ts id="txtHdg2">Heading 2</ts>
<ts id="txtHdg3">Heading 3</ts>
<ts id="txtHdg4">Heading 4</ts>
<ts id="txtHdg5">Heading 5</ts>
<ts id="txtHdg6">Heading 6</ts>
<ts id="txtHdgNorm">Normaal</ts>
<ts id="upf">Voortgang met bestand uploaden</ts>
<ts id="upfCancelUpF">Annuleren van het uploaden van:</ts>
<ts id="upfConfUpF">Druk op OK om bestand te uploaden:</ts>
<ts id="upfTo">Aan:</ts>
<ts id="upfUpF">Uploaden van bestand</ts>
<ts id="vaBlack">Zwart</ts>
<ts id="vaBlue">Blauw</ts>
<ts id="vaGreen">Groen</ts>
<ts id="vaRed">Rood</ts>
<ts id="vwp">Bekijk voorkeuren</ts>
<ts id="vwpColor">Lettertype &amp;kleur:</ts>
<ts id="vwpFont">Lettertype naam</ts>
<ts id="vwpSize">Lettertype grootte</ts>
<ts id="cmdAbsPos">Positie</ts>
<ts id="cmdANo">Geen uitlijning </ts>
<ts id="cmdBC">Achtergrondkleur</ts>
<ts id="cmdBCVal">Achtergrondkleurenlijst</ts>
<ts id="cmdLRB">Links-naar rechts tekst</ts>
<ts id="cmdLRE">Links naar rechts bewerken</ts>
<ts id="cmdMSW">Bewerken in Word</ts>
<ts id="cmdRLB">Rechts naar links tekst</ts>
<ts id="cmdRLE">Rechts naar links bewerken</ts>
<ts id="cmdSelA">Selecteer alles</ts>
<ts id="cmdSelNo">Selecteer niets</ts>
<ts id="cmdZAT">Boven tekst</ts>
<ts id="cmdZB">Verplaats naar achterkant</ts>
<ts id="cmdZBT">Onder tekst</ts>
<ts id="cmdZBw">Verplaats naar achteren</ts>
<ts id="cmdZF">Verplaats naar voorkant</ts>
<ts id="cmdZFw">Verplaats naar voren</ts>
<ts id="mnuDir">Tekst richting</ts>
<ts id="mnuPos">Positie van objecten</ts>
<ts id="sJustify">Justeren</ts>
<ts id="sLock">Vastzetten</ts>
<ts id="sMove">Bewegen</ts>
<ts id="sNormal">Normaal</ts>
<ts id="sPrint">Drukken</ts>
<ts id="sProp">Eigenschappen</ts>
<ts id="sTransparent">Doorzichtig</ts>
<ts id="btnMenus">Menu's</ts>
<ts id="cmdAddr">Adres</ts>
<ts id="licTrial">Dagen voordat de licentie afloopt</ts>
<ts id="cmdUnSty">Opmaakelementen van</ts>
<ts id="frmElements">formulier verwijderen</ts>
<ts id="frmForm">Formulier</ts>
<ts id="frmBBtn">Knop</ts>
<ts id="frmSBtn">Knop Verzenden</ts>
<ts id="frmRBtn">Beginwaarde-knop</ts>
<ts id="frmHiddenFld">Verborgen tekstveld</ts>
<ts id="frmTextFld">Tekstveld</ts>
<ts id="frmPasswordFld">Wachtwoord</ts>
<ts id="frmTextarea">Tekstgebied</ts>
<ts id="frmOptionBox">Keuzerondje</ts>
<ts id="frmCheckbox">Aankruisvakje</ts>
<ts id="frmDropList">Selecteren</ts>
<ts id="frmFormFile">Uploaden bestand</ts>
<ts id="mnu508table">Tabel sectie 508...</ts>
<ts id="mnuDS">(Opmaak toepassen)</ts>
<ts id="lblUsedAttr">Gebruikte kenmerken</ts>
<ts id="lblOfferAttr">Aangeboden kenmerken</ts>
<ts id="tagValue">Waarde</ts>
<ts id="tagAttrDlg">Speciale tag-kenmerken</ts>
<ts id="tagInsDlg">Speciale tag invoegen</ts>
<ts id="tagTags">Tags</ts>
<ts id="tagInsert">Invoegen</ts>
<ts id="tagNew">Nieuw</ts>
<ts id="tagDel">Wissen</ts>
<ts id="tagProp">Eigenschappen</ts>
<ts id="tagPropDlg">Speciale tag-eigenschappen</ts>
<ts id="tagProps">Tag-eigenschappen</ts>
<ts id="tagType">Type</ts>
<ts id="tagStyle">Informatie opmaak tag-naam </ts>
<ts id="tagDStyle">Informatie opmaak gegevensinhoud</ts>
<ts id="tagVisible">Naam weergeven</ts>
<ts id="tagEditable">Te wijzigen inhoud</ts>
<ts id="tagRender">Inhoud converteren</ts>
<ts id="tagGInfo">Tekeninformatie</ts>
<ts id="tagGVisible">Teken weergeven</ts>
<ts id="tagLoc">Locatie</ts>
<ts id="tagWd">Breedte</ts>
<ts id="tagHt">Hoogte</ts>
<ts id="sWordXmlWarn">WAARSCHUWING: deze inhoud bevat tags die wellicht niet worden herkend door Microsoft Word. Microsoft Word kan de inhoud beschadigen of ongeldige tags invoeren. 

Wilt u doorgaan?
</ts>
<ts id="findDir">Richting</ts>
<ts id="findUp">Omhoog</ts>
<ts id="findDn">Omlaag</ts>
<ts id="findFinish">Zoeken van het document voltooid</ts>
<ts id="mnuOLdec">Lijst: 1 2 3</ts>
<ts id="mnuOLloA">Lijst: a b c</ts>
<ts id="mnuOLupA">Lijst: A B C D</ts>
<ts id="mnuOLloR">Lijst: i ii iii</ts>
<ts id="mnuOLupR">Lijst: I I III IV</ts>
<ts id="mnuULdsc">Bullets: disc</ts>
<ts id="mnuULcir">Bullets: cirkel</ts>
<ts id="mnuULsqu">Bullets: vierkant</ts>
<ts id="mnuULnon">Bullets: geen</ts>
<ts id="cmdPasTxt">Tekst plakken</ts>
<ts id="cmdFindNext">Volgende zoeken</ts>
<ts id="cmdComment">Opmerkingen</ts>
<ts id="cmdNote">Opmerking</ts>
<ts id="cmdHilite">Highlight</ts>
<ts id="cmdOpen">Openen</ts>
<ts id="cmdSave">Opslaan</ts>
<ts id="sNoUpldCreate">De upload-module kon niet worden aangemaakt. Bestandsbewerking wordt afgebroken. Installeer opnieuw.</ts>
<ts id="sNoUpldFiles">Er zijn geen bestanden beschikbaar om te uploaden naar de server.</ts>
<ts id="sNoDispFile">Bestandselectie wordt afgebroken. Kon het volgende bestand niet weergeven:</ts>
<ts id="sUpldSure">U staat op het punt de geselecteerde content naar de server te verzenden. Wilt u nu verzenden?</ts>
<ts id="sFilesWtng">Bestanden wachten op uploaden</ts>
<ts id="sEstTime">Geschatte upload-tijd</ts>
<ts id="sUpldNow">Nu uploaden</ts>
<ts id="sUpldLater">Later uploaden</ts>
<ts id="stdAll">Alle</ts>
<ts id="stdNone">Geen</ts>
<ts id="sUpldFiles">Bestanden om te uploaden</ts>
<ts id="sUpldLogin">Login server voor uploaden bestanden</ts>
<ts id="sXferFile">Bestand wordt verzonden naar de server</ts>
<ts id="stdCancelAll">Alle annuleren</ts>
<ts id="cmdUpldFiles">Bestanden uploaden</ts>
<ts id="sNoUpldUnkwn">Het uploaden is mislukt vanwege een onbekende reden. De server kon het upload-verzoek niet verwerken.</ts>
<ts id="cmdMarkIns">Merkteken ingevoegd</ts>
<ts id="cmdMarkDel">Merkteken gewist</ts>
<ts id="sizBytes">bytes</ts>
<ts id="findRepAll">Alles vervangen</ts>
<ts id="findRepW">Vervangen door</ts>
<ts id="upfFin">Gereed</ts>
<ts id="mnucusttagattrs">Tag-kenmerken...</ts>
<ts id="mnuexttagprop">Bewerken Tag-eigenschappen...</ts>
<ts id="loadMSW">Microsoft Word 2000 of later is vereist</ts>
<ts id="filWarnTxt1">U staat op het punt uw MS Word document te wijzigen. Door de beperkingen van HTML, kan formatteringsinformatie verloren gaan als het document opnieuw wordt geopend in de opmaker.</ts>
<ts id="filWarnTxt2">U staat op het punt de huidige content van de editor te vervangen door de content van MS Word. Door de beperkingen van HTML, kan formatteringsinformatie verloren gaan als het document opnieuw wordt geopend in de editor.</ts>
<ts id="filWarnTxt3">Als u de Word-inhoud niet in de opmaker invoegt, zullen uw veranderingen verloren gaan.</ts>
<ts id="filWarnAsk1">Wilt u doorgaan?</ts>
<ts id="filWarnWinTitle">Bewerken in Word</ts>
<ts id="undoPreSave">Weet u zeker dat u alle wijzigingen ongedaan wilt maken en de vorige versie van het document wilt herstellen?</ts>
<ts id="redoPreSave">Weet u zeker dat u het document wilt herstellen dat dit heeft vervangen?</ts>
<ts id="loadimgederr">De opmaker kon de Image Editor niet maken. Gebruik het Image Edit installatieprogramma om deze voorziening te installeren.</ts>
<ts id="mnuMain">Hoofd</ts>
<ts id="mnuAnnotation">Opmerking</ts>
<ts id="btnFileMenu">Bestand</ts>
<ts id="btnEditMenu">Bewerken</ts>
<ts id="btnViewMenu">Beeld</ts>
<ts id="btnImageMenu">Beeld</ts>
<ts id="btnAnnotationsMenu">Opmerking</ts>
<ts id="btnCreateNew">Maak &amp;Nieuw</ts>
<ts id="btnOpen">&amp;Openen...</ts>
<ts id="xltCreateNew">Nieuw beeld maken</ts>
<ts id="xltOpen">Beeld openen...</ts>
<ts id="xltSave">Beeld opslaan</ts>
<ts id="btnSaveAs">Opslaan &amp;Als...</ts>
<ts id="xltSaveAs">Sla het bestand op met een bruikbare bestandsnaam of bestandsformaat.</ts>
<ts id="btnExit">S&amp;luiten</ts>
<ts id="xltExit">Dit venster sluiten</ts>
<ts id="btnImageInfo">&amp;Beeld Info...</ts>
<ts id="xltImageInfo">Toon beeld info</ts>
<ts id="btnThumbnail">&amp;Thumbnail...</ts>
<ts id="xltThumbnail">Thumbnail maken van huidig beeld</ts>
<ts id="btnColorDepth">Kleurdiepte...</ts>
<ts id="xltColorDepth">Kleurdiepte van huidig beeld veranderen</ts>
<ts id="btnContrast">Cont&amp;rast...</ts>
<ts id="xltContrast">Contrast van huidig beeld veranderen</ts>
<ts id="btnDimensions">&amp;Afmetingen...</ts>
<ts id="xltDimensions">Afmetingen van huidig beeld veranderen</ts>
<ts id="btnHorizFlip">&amp;Horizontaal draaien</ts>
<ts id="xltHorizFlip">Beeld draaien over horizontale as</ts>
<ts id="btnVertFlip">&amp;Verticaal draaien</ts>
<ts id="xltVertFlip">Beeld draaien over verticale as</ts>
<ts id="btnAnnotationToolbar">Om&amp;schakelen Opmerkingen Taakbalk</ts>
<ts id="xltAnnotationToolbar">Weergave van opmerkingshulpmiddelen omschakelen</ts>
<ts id="btnBlur">B&amp;eeld vervagen...</ts>
<ts id="xltBlur">Randen van het beeld vervagen</ts>
<ts id="btnBrightness">&amp;Helderheid...</ts>
<ts id="xltBrightness">Helderheid van het beeld veranderen</ts>
<ts id="xltCopy">Kopiëren</ts>
<ts id="btnCrop">Af&amp;knippen</ts>
<ts id="xltCrop">Afknippen</ts>
<ts id="xltCut">Knippen</ts>
<ts id="xltPaste">Plakken</ts>
<ts id="btnDelete">&amp;Wissen</ts>
<ts id="xltDelete">Wissen</ts>
<ts id="btnFullView">Zoom &amp;verhouding herstellen</ts>
<ts id="xltFullView">Zoom verhouding herstellen op 1:1</ts>
<ts id="btnPalette">&amp;Palet opmaken...</ts>
<ts id="xltPalette">Afbeeldingpalet bewerken</ts>
<ts id="xltRedo">Ongedaan gemaakte veranderingen overnieuw doen</ts>
<ts id="btnRotate">&amp;Roteren...</ts>
<ts id="xltRotate">Beeld roteren</ts>
<ts id="xltSelect">Beeld gebied selecteren</ts>
<ts id="btnSharpen">&amp;Verscherpen...</ts>
<ts id="xltSharpen">Beeld scherper maken</ts>
<ts id="xltText">Tekst aan beeld toevoegen</ts>
<ts id="xltUndo">Laatste verandering ongedaan maken</ts>
<ts id="btnZoomIn">Zoom &amp;In</ts>
<ts id="xltZoomIn">Zoom in op beeld</ts>
<ts id="btnZoomOut">Zoom &amp;Uit</ts>
<ts id="xltZoomOut">Zoom weg van beeld</ts>
<ts id="btnEraser">&amp;Opmerking verwijderen</ts>
<ts id="xltEraser">Huidig geselecteerde opmerking(en) verwijderen</ts>
<ts id="btnDeselect">&amp;Opmerkingen stoppen</ts>
<ts id="xltDeselect">Toevoegen van opmerkingen stoppen</ts>
<ts id="btnFloodFill">Op&amp;vullen</ts>
<ts id="xltFloodFill">Gemarkeerd gebied opvullen</ts>
<ts id="btnFreehand">&amp;Vrije hand</ts>
<ts id="xltFreehand">Met vrije hand tekenen</ts>
<ts id="btnLine">&amp;Lijn</ts>
<ts id="xltLine">Lijn tekenen</ts>
<ts id="btnOval">&amp;Ovaal</ts>
<ts id="xltOval">Ovaal tekenen</ts>
<ts id="btnPolygon">&amp;Polygoon</ts>
<ts id="xltPolygon">Polygoon tekenen</ts>
<ts id="btnRectangle">&amp;Rechthoek</ts>
<ts id="xltRectangle">Rechthoek tekenen</ts>
<ts id="btnSprayCan">&amp;Spuitbus</ts>
<ts id="xltSprayCan">Huidige kleur op beeld spuiten</ts>
<ts id="inf">Bestandsinformatie</ts>
<ts id="infDimension">Afmeting:</ts>
<ts id="infBitDepth">Bit Diepte:</ts>
<ts id="infImageSize">Beeldmaat:</ts>
<ts id="infFileFormat">Bestandsformaat:</ts>
<ts id="infCompression">Compressie:</ts>
<ts id="brg">Helderheid</ts>
<ts id="dpt">Kleurdiepte</ts>
<ts id="dpt1bit">&amp;1 bit (2 kleuren)</ts>
<ts id="dpt4bit">&amp;4 bit (16 kleuren)</ts>
<ts id="dpt8bit">&amp;8 bit (256 kleuren)</ts>
<ts id="dpt24bit">&amp;24 bit (16M kleuren)</ts>
<ts id="rot">Roteren</ts>
<ts id="rotDegree">Graad</ts>
<ts id="rotVarDegree">&amp;Vrij:</ts>
<ts id="rotLeft">&amp;Links</ts>
<ts id="rotRight">&amp;Rechts</ts>
<ts id="cst">Contrast</ts>
<ts id="shp">Verscherpen</ts>
<ts id="blr">Vervagen</ts>
<ts id="dms">Afmetingen</ts>
<ts id="dmsNewWdith">Nieuwe breedte:</ts>
<ts id="dmsNewHeight">Nieuwe hoogte:</ts>
<ts id="dmsCurrentWidth">Huidige breedte:</ts>
<ts id="dmsCurrentHeight">Huidige hoogte:</ts>
<ts id="epl">Palet bewerken</ts>
<ts id="noFileInfo">Bestandsinformatie is niet beschikbaar.</ts>
<ts id="promptSave">Gewijzigd bestand opslaan?</ts>
<ts id="noImGearCtl">Kon beeldcontroleregeling niet maken!</ts>
<ts id="noIGArtCtl">Kon beeldkunstcontroleregeling niet maken!</ts>
<ts id="SaveImgAsdlg">Beeld opslaan als</ts>
<ts id="thn">Thumbnail maken</ts>
<ts id="thnThumbnail">Thumbnail</ts>
<ts id="thnWidth">Thumbnail breedte:</ts>
<ts id="thnHeight">Thumbnail hoogte:</ts>
<ts id="btnCreate">&amp;Maken</ts>
<ts id="thnThumbnailSaveAs">Thumbnail opslaan als:</ts>
<ts id="taskDisabled">Deze functie is niet beschikbaar voor beelden kleiner dan 8 bit kleurdiepte.</ts>
<ts id="dmsAspectRatio">Beeldverhouding &amp;vasthouden</ts>
<ts id="noFilename">Selecteer een bestandsnaam voor de Thumbnail.</ts>
<ts id="btnTwain">TWAIN &gt; Op&amp;halen...</ts>
<ts id="cmdImgEdit">Beeld opmaker</ts>
<ts id="thnNoDisplay">Voorweergave thumbnail niet mogelijk.</ts>
<ts id="warnReadOnlyFile">Kan alleen-lezen bestand niet overschrijven.</ts>
<ts id="errbadwifxlic">Ongeldige licentie: Voor het WebImageFX product moet een licentie zijn gekocht voordat het kan werken. Neem contact op met uw Ektron leverancier voor aankoopinformatie.</ts>
<ts id="noWebPicCtl">Kon geen webpic regeling maken!</ts>
<ts id="btnUpldFiles">Beeld verzending</ts>
<ts id="picFailed404">Of de ontvangende pagina, of een vereiste pagina, bestaat niet op de server.</ts>
<ts id="cmdDDesign">Design tonen</ts>
<ts id="cmdGroupFld">Velden groeperen</ts>
<ts id="cmdFieldset">Vakje groeperen</ts>
<ts id="cmdBoolean">Aankruisvakje veld</ts>
<ts id="cmdPlainTxt">Gewone tekst veld</ts>
<ts id="cmdRichArea">Rijk gebied veld</ts>
<ts id="cmdChecklist">Checklist veld</ts>
<ts id="cmdChoiceFld">Keuze veld</ts>
<ts id="cmdListFld">Lijst veld selecteren</ts>
<ts id="cmdFldProp">Veld eigenschappen...</ts>
<ts id="cmdAddFld">Veld invoegen...</ts>
<ts id="cmdDEntry">Gegevensinvoer tonen</ts>
<ts id="mnuDesignBar">Gegevensdesign</ts>
<ts id="frmActPage">Actiepagina</ts>
<ts id="frmEncType">Type codering</ts>
<ts id="frmText">Tekst</ts>
<ts id="frmReqNam">Naam is vereist.</ts>
<ts id="frmReqVal">Waarde is vereist.</ts>
<ts id="frmDefIsChk">Standaard is gecontroleerd.</ts>
<ts id="frmSelDefault">Standaard geselecteerd.</ts>
<ts id="frmSize">Grootte</ts>
<ts id="frmColumns">Kolommen</ts>
<ts id="frmRows">Rijen</ts>
<ts id="frmMethod">Methode</ts>
<ts id="frmOptionPost">posten</ts>
<ts id="frmOptionGet">ontvangen</ts>
<ts id="frmOptionApplication">application/x-www-form-urlencoded (standaard)</ts>
<ts id="frmOptionMultipart">multipart/form-data (vereist wanneer INPUT TYPE=FILE)</ts>
<ts id="frmOptionText">text/plain (voor verzenden: alleen)</ts>
<ts id="frmAllowMultiple">Meerdere opties</ts>
<ts id="frmOptionQty">toestaan</ts>
<ts id="frmOptionName">Benaming optie</ts>
<ts id="frmDisplayValue">Beeldwaarde</ts>
<ts id="frmBtnInsert">Invoegen</ts>
<ts id="frmBtnContinue">Doorgaan</ts>
<ts id="frmMsgAlertNumber">Het item moet een getal zijn:</ts>
<ts id="frmMsgAlertQtyFld">Aantal opties dient groter te zijn dan nul (0).</ts>
<ts id="frmMsgOptName">Benaming optie  is vereist.</ts>
<ts id="cmdcontupload">Content verzending</ts>
<ts id="mnuInsAbv">Hierboven invoegen</ts>
<ts id="mnuInsBel">Hieronder invoegen</ts>
<ts id="mnuDupl">Dupliceren</ts>
<ts id="mnuMvUp">Omhoog verplaatsen</ts>
<ts id="mnuMvDn">Omlaag verplaatsen</ts>
<ts id="mnuRem">Verwijderen</ts>
<ts id="sFld">Veld</ts>
<ts id="sInvFld">Minstens een veld in ongeldig. Corrigeren en opnieuw proberen.</ts>
<ts id="dlgName">Naam</ts>
<ts id="dlgDispName">Naam tonen</ts>
<ts id="dlgDefVal">Standaard waarde</ts>
<ts id="dlgVal">Waarde</ts>
<ts id="dlgTxt">Tekst</ts>
<ts id="dlgChkT">Waar (aangekruist)</ts>
<ts id="dlgChkF">Onwaar (niet aangekruist)</ts>
<ts id="dlgChkd">Aangekruist</ts>
<ts id="dlgCaption">Bijschrift</ts>
<ts id="dlgAllow">Toestaan</ts>
<ts id="dlgAllowSel">Selectie toestaan</ts>
<ts id="dlgOnly1">Slechts een</ts>
<ts id="dlgMore1">Meer dan een</ts>
<ts id="dlgVLst">Verticale lijst</ts>
<ts id="dlgHLst">Horizontale lijst</ts>
<ts id="dlgSel">Selecteer</ts>
<ts id="dlgSeld">Geselecteerd</ts>
<ts id="dlgApprnce">Vormgeving</ts>
<ts id="dlgShowBox">Toon vak en bijschrift</ts>
<ts id="dlgNBorder">Geen rand</ts>
<ts id="dlgFields">Velden</ts>
<ts id="dlgUse">Gebruiken</ts>
<ts id="dlgReqd">Vereist</ts>
<ts id="dlgOpt">Optioneel</ts>
<ts id="dlgV8n">Bevestiging</ts>
<ts id="dlgNV8n">Geen bevestiging</ts>
<ts id="dlgNBlank">Kan niet leeg zijn</ts>
<ts id="dlgNNN">Niet-negatief geheel getal of leeg</ts>
<ts id="dlgNNNReqd">Niet-negatief geheel getal (vereist)</ts>
<ts id="badsrvr">Kan geen verbinding maken met de server. Verzending is niet mogelijk.</ts>
<ts id="connerror">Fout in de verbinding.</ts>
<ts id="filexfererr">Fout in de bestandsoverdracht.</ts>
<ts id="cmdCopy">Kopiëren</ts>
<ts id="btnAnnotationColor"></ts>
<ts id="xltAnnotationColor"></ts>
<ts id="btnAnnotationFont"></ts>
<ts id="xltAnnotationFont"></ts>
<ts id="btnSelect">Selecteren</ts>
<ts id="btnPasteNew">Plakken</ts>
<ts id="xltPasteNew">Plakken</ts>
<ts id="sas">Opslaan Als</ts>
<ts id="btnPointer">&amp;Pointer</ts>
<ts id="xltPointer">Select Annotations</ts>
<ts id="btnTwainSource">TWAIN Source...</ts>
<ts id="xltTwainSource">Select TWAIN source</ts>
<ts id="filHX">All Files (*.*)|*.*|HTML Documents (*.htm*)|*.htm*|XML Documents (*.xml)|*.xml</ts>
<ts id="dmsMsgMaxExceed">The specified dimensions have exceed the maximum allowed.  Please reduce the values.</ts>
<ts id="warnCopyArts">Would you like to copy annotations as well?  If so, we'll burn the annotations into the image and you won't be able to edit them any longer.</ts>
<ts id="warnCutArts">Would you like to cut annotations as well?  If so, we'll burn the annotations into the image and you won't be able to edit them any longer.</ts>
<ts id="warnDelArts">Would you like to delete annotations in this as well?  If so, we'll burn the annotations into the image and you won't be able to edit them any longer.</ts>
<ts id="warnInvJPEGbit">Invalid bitcount (depth) for JPEG.</ts>
<ts id="warnFileOverwrite">Overwrite existing file?</ts>
<ts id="warnFileExist">File Exists</ts>
<ts id="dlgImgLoad">Load Image</ts>
<ts id="dlgArtsDefColor">Select Default Annotation Color</ts>
<ts id="dlgArtsDefFont">Select Default Annotation Font</ts>
<ts id="btnExitNoSave">Exit without save</ts>
<ts id="xltExitNoSave">Close this image editing session without saving</ts>
<ts id="warnJPGBitSaved">Due to the limitations of the specified file format, your image is saved in true color format.</ts>
<ts id="xferDispName">Server</ts>
<ts id="sOrMore">or more</ts>
<ts id="sTo">to</ts>
<ts id="sCurFld">(current field)</ts>
<ts id="valSelFG">&amp;Select a Field or Group</ts>
<ts id="dlgCustom">(Custom)</ts>
<ts id="val">Custom Validation</ts>
<ts id="valCustVal">&amp;Custom Validation...</ts>
<ts id="valDT">Data Type</ts>
<ts id="valDT2">Data &amp;Type:</ts>
<ts id="valCalc">Calculation</ts>
<ts id="valConditn">&amp;Condition:</ts>
<ts id="valSel">&amp;Select Field...</ts>
<ts id="valVal">Validation</ts>
<ts id="valMsg">Error &amp;Message:</ts>
<ts id="cmdVal">Validate</ts>
<ts id="cmdValayt">Validate As You Type</ts>
<ts id="valCV">The content is valid.</ts>
<ts id="sUniqName">Fields within the same group must have unique names.</ts>
<ts id="sDupFld">Duplicate field name:</ts>
<ts id="sPText">Plain text</ts>
<ts id="sURL">URL</ts>
<ts id="sWhNum">Whole number</ts>
<ts id="sDecNum">Decimal number</ts>
<ts id="sFPNum">Floating point number</ts>
<ts id="cmdCalcFld">Calculated Field</ts>
<ts id="valEx">&amp;Examples</ts>
<ts id="nhkFileExp">File Explorer</ts>
<ts id="imgSvrFile">Server &amp;Files:</ts>
<ts id="imgSel">&amp;Select:</ts>
<ts id="dlgItemLst">Item List</ts>
<ts id="dlgItem">Item</ts>
<ts id="tagIdx">Indexed</ts>
<ts id="dlgMultiLine">Allow multiple lines</ts>
<ts id="dlgReadOnly">Cannot be changed</ts>
<ts id="dlgHidden">Invisible</ts>
<ts id="dlgURL">Image Location:</ts>
<ts id="dlgDefURL">Default Image Location:</ts>
<ts id="tblSvr">From Server...</ts>
<ts id="dlgFileURL">File Location:</ts>
<ts id="sAdd2N">Add two numbers</ts>
<ts id="sSub2N">Subtract two numbers</ts>
<ts id="sMul2N">Multiply two numbers</ts>
<ts id="sDiv2N">Divide two numbers</ts>
<ts id="sFmtPct">Format as a percentage</ts>
<ts id="sAbsVal">Absolute value of a number</ts>
<ts id="s0IfNeg">Zero if subtraction is negative</ts>
<ts id="sMulIf">Multiply by another number if a checkbox is checked</ts>
<ts id="sRnd">Round a decimal number</ts>
<ts id="sRndUp">Round up a decimal number</ts>
<ts id="sRndDn">Round down a decimal number</ts>
<ts id="sTotFlds">Total numeric values from multiple fields</ts>
<ts id="sTotList">Total a list of numeric values</ts>
<ts id="sAveList">Average a list of numeric values</ts>
<ts id="sCntList">Count the number of values in a list</ts>
<ts id="sLCase">Lowercase text</ts>
<ts id="sUCase">Uppercase text</ts>
<ts id="sRemSp">Remove extra spaces</ts>
<ts id="sConcat">Concatenate text</ts>
<ts id="sSzTxt">Size of a text string</ts>
<ts id="sPctReqd">Percent: 0-100 (required)</ts>
<ts id="sZIP">ZIP Code (U.S.)</ts>
<ts id="sSSN">Social Security Number (U.S.)</ts>
<ts id="sN2Vals">Number between two values</ts>
<ts id="sEquN">Must equal another number</ts>
<ts id="sNeqN">Must not equal another number</ts>
<ts id="sMaxLen">Maximum text length</ts>
<ts id="sGTN">Greater than another number</ts>
<ts id="sLTN">Less than another number</ts>
<ts id="sNNN">Non-negative number</ts>
<ts id="cmdCalendar">Calendar Field</ts>
<ts id="cmdFileLink">File Link Field</ts>
<ts id="cmdImageOnly">Image Only Field</ts>
<ts id="nhkOptMsg">Check item to be selected by default.</ts>
<ts id="dlgBadExt">The selected file is not a valid file format to allow an upload.</ts>
<ts id="picSvrFile">Select &amp;Server File</ts>
<ts id="valFormula">Formula:</ts>
<ts id="dlgDefDesc">Default File Description:</ts>
<ts id="dlgDefFileURL">Default File Location:</ts>
<ts id="sSelDate">Select Date</ts>
<ts id="sSelPict">Select Image</ts>
<ts id="sSelFile">Select File</ts>
<ts id="dlgDate">Date:</ts>
<ts id="dlgImg">Image:</ts>
<ts id="dlgDesc">File Description:</ts>
<ts id="sMin2">Minimum of two numbers</ts>
<ts id="sMax2">Maximum of two numbers</ts>
<ts id="frmMsgDuplVal">Duplicate item value is detected.  Please correct the item value for content validation.</ts>
<ts id="sDecN">Decimal number or blank</ts>
<ts id="sDecN2Reqd">Decimal number .00 (required)</ts>
<ts id="sFNVar">An expression still contains a field name variable</ts>
<ts id="stdCont">Do you want to continue?</ts>
<ts id="upfErr">Error in Uploading:</ts>
<ts id="sFmtDecN2">Format decimal number 0.00</ts>
<ts id="installcomplete">If successful, this window will close automatically.</ts>
<ts id="msgEwepLoader">eWebEditPro client installed.</ts>
<ts id="msgWifxLoader">WebImageFX client installed.</ts>
<ts id="picWarnFolder">Sorry, the FTP folder specified cannot be found.  Please verify that the FTP transfer information are correct.</ts>
<ts id="sErrCal">Error:  Unable to load the Microsoft Calendar Control.</ts>
<ts id="sBrowse">Browse</ts>
<ts id="sERR_ADMIN">You do not have the Administrator privilege that is required to install this application.
This installation may fail but you may choose to continue.
Would you like to continue the installation?</ts>
<ts id="cmdBtn">Button</ts>
<ts id="sSelBtn">(Select Button)</ts>
<ts id="sSel">(Select)</ts>
<ts id="dlgItem1Inv">First item is not a valid selection. For example, "(Select)"</ts>
<ts id="dlgSelReqd">A selection is required</ts>
<ts id="dlgUA">Unassigned</ts>
<ts id="dlgDS">Data Style...</ts>
<ts id="dlgList">List:</ts>
<ts id="dvs">Data Value Style</ts>
<ts id="dvsBold">Bold:</ts>
<ts id="dvsItalic">Italic:</ts>
<ts id="dvsTxtAlign">Text Alignment:</ts>
<ts id="dvsTxtLn">Text Line:</ts>
<ts id="sNoLngAvail">No longer available</ts>
<ts id="sEmailAddr">Email address</ts>
<ts id="sCountries">Countries</ts>
<ts id="sUSState">U.S. States &amp; Territories</ts>
<ts id="sCaPrvnc">Canadian Provinces</ts>
<ts id="sAgeRng">Age Ranges</ts>
<ts id="sNumRng">Numeric Ranges</ts>
<ts id="sYrs">Years</ts>
<ts id="cmdPrevw">Preview</ts>
<ts id="cmdTabData">Tabular Data Box</ts>
<ts id="tdbRows">Rows</ts>
<ts id="tdbRNam">Row Name:</ts>
<ts id="tdbRDispNam">Row Display Name:</ts>
<ts id="tdbMinNum">Minimum Number:</ts>
<ts id="tdbMaxNum">Maximum Number:</ts>
<ts id="tdbCols">Columns:</ts>
<ts id="dlgUnlim">Unlimited</ts>
<ts id="cmdViewXSD">Schema</ts>
<ts id="cmdViewDat">Data as XML</ts>
<ts id="cmdViewXSL">XSLT</ts>
<ts id="cmdViewIdx">Index</ts>
<ts id="sMergeMarkPrompt">In order to continue your action, this image must be reduced to a single background layer. Would you like to merge the layers now?</ts>
<ts id="warnMergeLayers">Merge Image Layers</ts>
<ts id="mnuARow">Add Row</ts>
<ts id="mnuACol">Add Column</ts>
<ts id="sLanguages">Languages</ts>
<ts id="sFldHdg">Field Heading</ts>
<ts id="sInsFld">Insert field here</ts>
<ts id="calNoDate">Remove date</ts>
<ts id="tbl508Form">Accessibility</ts>
<ts id="tbl508Abbr">Abbreviation:</ts>
<ts id="tbl508Axis">Categories:</ts>
<ts id="tbl508MsgResetHeadCols">It has been reset to zero(0).</ts>
<ts id="tbl508HeadRows">Eerste rij:</ts>
<ts id="tbl508HeadCols">Eerste kolom:</ts>
<ts id="tbl508Summary">Samenvatting:</ts>
<ts id="tbl508Caption">Bijschrift:</ts>
<ts id="tbl508HCaption">Horizontale uitlijning opschriften:</ts>
<ts id="tbl508MsgIllegalHeadRows">Het aantal titelrijen is groter dan het toegestane maximum.</ts>
<ts id="tbl508MsgIllegalHeadCols">Het aantal titelkolommen is groter dan het toegestane maximum.</ts>
<ts id="tbl508MsgWarnHeadCols">Er kunnen geen titelkolommen worden ingesteld.</ts>
<ts id="OptionLeft">Links</ts>
<ts id="OptionCenter">Midden</ts>
<ts id="OptionRight">Rechts</ts>
<ts id="OptionTop">Boven</ts>
<ts id="OptionBottom">Onder</ts>
<ts id="tbl508VCaption">Vertical Caption Alignment:</ts>
<ts id="sDate">Date</ts>
<ts id="sDateAfter">Date After</ts>
<ts id="sDateBefore">Date Before</ts>
<ts id="sPwd">Password Field</ts>
<ts id="sReqd">(required)</ts>
<ts id="sPCCA">Postal Code (Canada)</ts>
<ts id="sSIN">Social Insurance Number (Canada)</ts>
<ts id="sPhoneUSCA">Telephone Number (US and Canada)</ts>
<ts id="cmdFDesign">Form Design</ts>
<ts id="mnuFORM">View Form</ts>
<ts id="mnuMisc">Miscellaneous</ts>
<ts id="sErrXSLTStream">XSLT Stream not supported for transformation instructions.</ts>
<ts id="sErrWGDataType">The element has an invalid value according to its data type.</ts>
<ts id="sElemName">Element name:</ts>
<ts id="sErrEmptyElem">Element cannot be empty according to the Schema.</ts>
<ts id="sErrWGNumOfRow">The number of rows is less than the minimum number of rows defined.</ts>
<ts id="sErrRootTagNoMatch">The specified root tag does not match what was set.</ts>
<ts id="sErrRootTagForDisplay">Cannot set the root tag.  The root tag is displayed for editing.</ts>
<ts id="sErrNoXMLDoc">Cannot set the root tag.  We do not have an XML document.</ts>
<ts id="sErrEmptyRootTag">Cannot set the root tag.  The given root tag is empty.</ts>
<ts id="sErrCannotSetRootTag">Cannot set the root tag.  May be displaying the root tag, or we don't have an XML document, or the root tag is empty.</ts>
<ts id="sErrSchemaLibraryLoadErr">Schema library not available.</ts>
<ts id="sErrInvalidNamespace">Invalid namespace for creating XML document template.</ts>
<ts id="sErrFunctionalityNotSupported">Installed XML Parser does not support transformation.</ts>
<ts id="sErrDocumentBad">The specified XSLT file does not exist.</ts>
<ts id="sFilename">Filename:</ts>
<ts id="sErrXSLTNotLoad">The XSLT failed to load.</ts>
<ts id="mnuIndent">Indent</ts>
<ts id="mnuHIndent">Hanging Indent</ts>
<ts id="sItem1Inv">First item is not a valid selection.</ts>
<ts id="dlgListBox">List Box</ts>
<ts id="sPwd8StrReqd">Minimum of eight (8) characters with at least one digit</ts>
<ts id="sSelLink">Select...</ts>
<ts id="sDefault">Default</ts>
<ts id="sMax1000Chars">Allow maximum of 1000 characters</ts>
<ts id="sSubmit">Submit</ts>
<ts id="sReset">Reset</ts>
<ts id="sGender">Gender</ts>
<ts id="sMale">Male</ts>
<ts id="sFemale">Female</ts>
<ts id="sMariStatus">Marital Status</ts>
<ts id="sDivorced">Divorced</ts>
<ts id="sLSeparated">Legally Separated</ts>
<ts id="sMarried">Married</ts>
<ts id="sPartner">Registered Domestic Partner</ts>
<ts id="sSeparated">Separated</ts>
<ts id="sSingle">Single</ts>
<ts id="sUMarried">Unmarried</ts>
<ts id="sUReported">Unreported</ts>
<ts id="sWidowed">Widowed</ts>
<ts id="sErrDefaultNS">The editor has detected that a default namespace is declared in the configuration. As a result, the data list may not be processed correctly.</ts>
<ts id="sDataList">Data list</ts>
<ts id="sNamespaces">Namespaces</ts>
<ts id="sErrNoFile">File Not Found.</ts>
<ts id="mnuXSLT">View Presentation</ts>
<ts id="cmdPDesign">Presentation Design</ts>
<ts id="cmdMergeLst">Merge List</ts>
<ts id="cmdMergeFld">Merge Field</ts>
<ts id="slstStyle">List Style</ts>
<ts id="sHorzTable">Horizontal Table Formatted</ts>
<ts id="sVertTable">Vertical Table Formatted</ts>
<ts id="sHeadingList">Heading Formated</ts>
<ts id="sDelimitedList">Delimited List</ts>
<ts id="sToolTip">Tool Tip Text:</ts>
<ts id="sFieldName">Field Name:</ts>
<ts id="sDescriptive">Descriptive Name:</ts>
<ts id="sEmailAddrList">Email address list</ts>
<ts id="mnuIColR">Insert Column to the Right</ts>
<ts id="mnuIRowB">Insert Row Below</ts>
<ts id="mnuMRowU">Move Rows Up</ts>
<ts id="mnuMRowD">Move Rows Down</ts>
<ts id="mnuMColL">Move Columns Left</ts>
<ts id="mnuMColR">Move Columns Right</ts>
<ts id="sAccessKey">Accelerator Key:</ts>
<ts id="sAdvanced">Advanced</ts>
<ts id="sBasic">Basic</ts>
<ts id="sShortcutKey">Keyboard Shortcut: </ts>
<ts id="vwpBgColor">Background:</ts>
<ts id="sMsg">Message</ts>
<ts id="sWrap">Word Wrap</ts>
<ts id="sErrNotXml">The content is not valid XML and cannot be saved as it is.</ts>
<ts id="sDiscard">To discard your changes, click OK, otherwise, click Cancel."</ts>
<ts id="afp">Advanced Field Properties</ts>
<ts id="afpType">Type</ts>
<ts id="afpElem">Element</ts>
<ts id="afpAttr">Attribute</ts>
<ts id="afpCont">Content</ts>
<ts id="afpRoot">Root Tag</ts>
<ts id="afpUseRoot">Use &lt;root&gt; as the root tag</ts>
<ts id="afpUseThis">Use this element as the root tag</ts>
<ts id="afpGroup">GroupName</ts>
<ts id="afpValue">Value</ts>
<ts id="dlgAdv">Advanced...</ts>
<ts id="sEg">e.g.,</ts>
<ts id="sContentLC">(content)</ts>
<ts id="cmdViewFld">Field List</ts>
<ts id="WarnAccessCompliance">The content is not accessibility compliant.</ts>
<ts id="PromptEditAccess">Would you like to correct it?</ts>
<ts id="RequestEditAccess">Please fill in the accessibility compliance field(s).</ts>
<ts id="AccessCompliance">Accessibility Compliance</ts>
<ts id="AccessHeader">Web Accessibility Compliance Report</ts>
<ts id="ErrOnlineValidateMsg">Content is invalid. Online validation site:</ts>
<ts id="ErrXSLTValidateMsg">Content is invalid. XSL transform:</ts>
<ts id="cmdMath">Mathematical Expression</ts>
<ts id="dlgImgProp">Image Properties</ts>
<ts id="mnuEMath">Edit Math...</ts>
<ts id="sNoWebEQ">The WebEQ3 applet is not installed.</ts>
<ts id="sNoJVM">Sun Java (JVM) is required. Visit http://java.com/getjava.</ts>
<ts id="sNoJVM14">Sun Java (JVM) version 1.4 is required. Visit http://java.sun.com/j2se/1.4.2/download.html.</ts>
<ts id="licGrace">License expired. Days left: </ts>
<ts id="sErrDnld">Unable to download file: </ts>
<ts id="licEval">Evaluation license. Days left: </ts>
<ts id="picInsertImg">&amp;Insert Image</ts>
<ts id="sNotReady">The Document Is Not Ready</ts>
<ts id="sExtremeTime">Extreme Document Load Time:</ts>
<ts id="sQuestionWait">Do you wish to wait up to two (2) minutes for the document to complete?</ts>
<ts id="sWaitReason1">The document is in the process of resolving links.  While this is occurring, the document may not be fully available for retrieval.</ts>
<ts id="sWaitReason2">During this process some portions of the document may not be available.  If this operation continues some items may be lost.</ts>
<ts id="sWait">Wait for Document</ts>
<ts id="sNotWait">Do not wait</ts>
<ts id="clnProcess">Processing tags...</ts>
<ts id="sValidating">Validating Content...</ts>
<ts id="licVer">License version:</ts>
<ts id="noImgEditMath">WebImageFX is not able to edit this image.  A math image can only be edited with the Mathematical Expression editor.</ts>
<ts id="sISBN">ISBN</ts>
<ts id="sISSN">ISSN</ts>
<ts id="sVista">Vista</ts>
<ts id="sVistaUpld">On the Vista operating system local files cannot be displayed in content that is hosted on a server.  There are local images or files in the content going into the editor.  You must upload the images now or you will not be able to view them from the content you are editing.  Do you want to perform the upload now?</ts>
<ts id="sVistaImgs">Local images will not display in the content you are editing.  To view the images please select the Automatic-Upload feature and upload the images to the server.</ts>
<ts id="prepSelLocFile">Preparing Image Selection ... Please Wait ...</ts>
<ts id="sGTbN">The Google Toolbar Notifier is known to conflict with this editor.
The browser may freeze or simply disappear during the normal use of the editor.
The Google Toolbar Notifier has been disabled to avoid this problem.
Please restart the browser for the change to take effect.</ts>
<ts id="sInvDef">At least one field has a default value that fails validation.</ts>
<ts id="sInvName">At least one field has an invalid field name. Names are required, must start with a letter, and not contain spaces, colons or several other characters.</ts>
</standard>
</locale>
